cvr_osc_lib/__init__.py
cvr_osc_lib/osc_interface.py
cvr_osc_lib/osc_messages_data.py
cvr_osc_lib-0.0.9.dist-info/METADATA
cvr_osc_lib-0.0.9.dist-info/WHEEL
cvr_osc_lib-0.0.9.dist-info/licenses/LICENSE
cvr_osc_lib-0.0.9.dist-info/RECORD
