Metadata-Version: 2.1
Name: cvr-osc-lib
Version: 0.0.9
Summary: A small library to interface with CVR Melon Loader OSC mod API
Project-URL: Homepage, https://github.com/kafeijao/cvr_osc_lib_py
Project-URL: Bug Tracker, https://github.com/kafeijao/cvr_osc_lib_py/issues
Author-email: kafeijao <kafeijao@gmail.com>, novavoidhowl <me@novavoidhowl.com>
License-File: LICENSE
Classifier: License :: OSI Approved :: GNU General Public License v3 (GPLv3)
Classifier: Operating System :: OS Independent
Classifier: Programming Language :: Python :: 3
Requires-Python: >=3.9
Requires-Dist: python-osc<2,>=1.8.0
Provides-Extra: dev
Requires-Dist: pre-commit; extra == 'dev'
